mcp_scholar/__init__.py
mcp_scholar/scholar.py
mcp_scholar/server.py
mcp_scholar-0.2.0.dist-info/METADATA
mcp_scholar-0.2.0.dist-info/WHEEL
mcp_scholar-0.2.0.dist-info/entry_points.txt
mcp_scholar-0.2.0.dist-info/RECORD
