Metadata-Version: 2.4
Name: mcp_scholar
Version: 0.2.0
Summary: MCP Scholar for Google Scholar search
Requires-Python: >=3.10
Requires-Dist: beautifulsoup4>=4.13.3
Requires-Dist: httpx>=0.28.1
Requires-Dist: lxml>=4.9.3
Requires-Dist: mcp[cli]>=1.4.1
Requires-Dist: python-dotenv>=1.0.1
Requires-Dist: scholarly>=1.7.0
